chalice_babel/__init__.py
chalice_babel/lazy_string.py
chalice_babel/command/__init__.py
chalice_babel/command/main.py
chalice_babel-1.1.0.dist-info/LICENSE
chalice_babel-1.1.0.dist-info/METADATA
chalice_babel-1.1.0.dist-info/WHEEL
chalice_babel-1.1.0.dist-info/entry_points.txt
chalice_babel-1.1.0.dist-info/top_level.txt
chalice_babel-1.1.0.dist-info/RECORD
