Metadata-Version: 2.1
Name: chalice-babel
Version: 1.1.0
Summary: Chalice Babel Package
Home-page: https://github.com/sufleio/chalice-babel
Author: Sufle
Author-email: info@sufle.io
License: MIT
Classifier: Development Status :: 5 - Production/Stable
Classifier: License :: OSI Approved :: MIT License
Classifier: Operating System :: OS Independent
Classifier: Programming Language :: Python
Classifier: Programming Language :: Python :: 3
Classifier: Programming Language :: Python :: 3.6
Classifier: Programming Language :: Python :: 3.7
Classifier: Programming Language :: Python :: 3.8
Classifier: Programming Language :: Python :: 3.9
Classifier: Programming Language :: Python :: 3.10
Classifier: Environment :: Web Environment
Classifier: Intended Audience :: Developers
Classifier: Topic :: Software Development :: Libraries :: Python Modules
Requires-Python: >=3.6
License-File: LICENSE
Requires-Dist: Babel (>=2.10.3)
Requires-Dist: chalice (>=1.26.6)
Requires-Dist: Jinja2 (>=3.1.2)
Requires-Dist: pytz (>=2022.5)
Requires-Dist: Werkzeug (>=2.2.2)
Provides-Extra: dev
Requires-Dist: pytest ; extra == 'dev'
Requires-Dist: pytest-mock ; extra == 'dev'
